<?xml version = '1.0' encoding = 'UTF-8'?>
<Relation class="oracle.dbtools.crest.model.design.logical.Relation" name="has" directorySegmentName="seg_0" id="E3139A96-3C55-6B87-1E54-61BAF7FA3DE1">
<createdBy>pc</createdBy>
<createdTime>2022-12-15 19:01:02 UTC</createdTime>
<ownerDesignName>project3</ownerDesignName>
<importedID>7DED3D66-C6D9-C053-9476-BE795027A263</importedID>
<engineerTo>
<item key="F2487F03-8955-26F6-CE02-29DFAA02A94A" value="true"/>
<item key="3132FF99-1754-67CA-2E69-5A6334CB2DA3" value="true"/>
</engineerTo>
<sourcePk>455492C2-5A65-511D-5964-8E0176D017F9</sourcePk>
<identifying>true</identifying>
<optionalSource>true</optionalSource>
<optionalTarget>false</optionalTarget>
<sourceCardinality>1</sourceCardinality>
<sourceEntity>AD88837C-C782-392B-3B10-3B917B0E0455</sourceEntity>
<targetCardinalityString>*</targetCardinalityString>
<targetEntity>1A365F3D-5E87-525D-4944-9A903D261897</targetEntity>
<transferable>true</transferable>
<deleteRule>NO ACTION</deleteRule>
</Relation>
